okx/Account.py
okx/BlockTrading.py
okx/Convert.py
okx/CopyTrading.py
okx/Earning.py
okx/FDBroker.py
okx/Funding.py
okx/Grid.py
okx/MarketData.py
okx/NDBroker.py
okx/PublicData.py
okx/SimpleEarnFixed.py
okx/SpreadTrading.py
okx/Status.py
okx/SubAccount.py
okx/Trade.py
okx/TradingData.py
okx/__init__.py
okx/consts.py
okx/exceptions.py
okx/okxclient.py
okx/utils.py
okx/websocket/WebSocketFactory.py
okx/websocket/WsPrivateAsync.py
okx/websocket/WsPublicAsync.py
okx/websocket/WsUtils.py
okx/websocket/__init__.py
python_okx_earn-0.3.5.dist-info/METADATA
python_okx_earn-0.3.5.dist-info/WHEEL
python_okx_earn-0.3.5.dist-info/top_level.txt
python_okx_earn-0.3.5.dist-info/RECORD
